Metadata-Version: 2.1
Name: AtomicAI
Version: 0.3.0
Summary: Processing and visualization of atomic coordinates 
Home-page: https://sites.google.com/view/selvas
Author: Selva Chandrasekaran Selvaraj
Author-email: selvachandrasekar.s@gmail.com
License: MIT
Project-URL: Bug Tracker, https://github.com/SelvaGith/AtomicAI/issues
Project-URL: Source, https://github.com/SelvaGith/AtomicAI
Project-URL: Twitter, https://twitter.com/selva_odc
Project-URL: LinkedIn, https://www.linkedin.com/in/SelvaCS/?original_referer=https%3A%2F%2Fwww.google.com%2F
Project-URL: Scopus, https://www.scopus.com/authid/detail.uri?authorId=57225319817
Project-URL: Scholar, https://scholar.google.com/citations?user=vNozeNYAAAAJ&hl=en
Classifier: Intended Audience :: Science/Research
Classifier: Programming Language :: Python :: 3.9
Classifier: License :: OSI Approved :: GNU General Public License v3 (GPLv3)
Requires-Python: >=3.9
License-File: LICENSE.md
Requires-Dist: pip (>=22.1.2)
Requires-Dist: wheel (>=0.37.1)
